arcana/spaces/__init__.py
arcana/spaces/_version.py
arcana/spaces/data/__init__.py
arcana/spaces/data/clinical.py
arcana/spaces/data/samples.py
arcana/spaces/data/tests/test_clinical_space.py
arcana_spaces-0.1.0.dist-info/LICENSE
arcana_spaces-0.1.0.dist-info/WHEEL
arcana_spaces-0.1.0.dist-info/METADATA
arcana_spaces-0.1.0.dist-info/RECORD
