Metadata-Version: 2.1
Name: arcana-spaces
Version: 0.1.0
Summary: Description for arcana-spaces goes here
Keywords: arcana
Author-email: "Thomas G. Close" <tom.g.close@gmail.com>
Maintainer-email: "Thomas G. Close" <tom.g.close@gmail.com>
Requires-Python: >=3.8
Classifier: Development Status :: 2 - Pre-Alpha
Classifier: Environment :: Console
Classifier: Intended Audience :: Science/Research
Classifier: License :: OSI Approved :: Apache Software License
Classifier: Operating System :: MacOS :: MacOS X
Classifier: Operating System :: POSIX :: Linux
Classifier: Programming Language :: Python :: 3
Classifier: Topic :: Scientific/Engineering
Requires-Dist: arcana-core >=0.8.0
Requires-Dist: pre-commit ; extra == "dev"
Requires-Dist: packaging ; extra == "doc"
Requires-Dist: docutils>=0.10 ; extra == "doc"
Requires-Dist: mock>1.0 ; extra == "doc"
Requires-Dist: sphinx >=2.1.2 ; extra == "doc"
Requires-Dist: sphinx-argparse>=0.2.0 ; extra == "doc"
Requires-Dist: sphinx-click>=3.1 ; extra == "doc"
Requires-Dist: furo>=2022.2.14.1 ; extra == "doc"
Requires-Dist: numpydoc>=0.6.0 ; extra == "doc"
Requires-Dist: pytest >= 4.4.0 ; extra == "test"
Requires-Dist: pytest-cov ; extra == "test"
Requires-Dist: pytest-env ; extra == "test"
Requires-Dist: codecov ; extra == "test"
Provides-Extra: dev
Provides-Extra: doc
Provides-Extra: test
